lye/__init__.py
lye/audio.py
lye/browser.py
lye/command_line.py
lye/files.py
lye/image.py
lye/notion.py
lye/slack.py
lye/wandb_workspaces.py
lye/web.py
lye/utils/__init__.py
lye/utils/files.py
lye/utils/logging.py
slide_lye-6.3.0.dist-info/METADATA
slide_lye-6.3.0.dist-info/WHEEL
slide_lye-6.3.0.dist-info/RECORD
