Metadata-Version: 2.4
Name: slide-lye
Version: 6.3.0
Summary: Lye - Tools package for Tyler AI framework
Project-URL: Homepage, https://github.com/adamwdraper/slide
Project-URL: Repository, https://github.com/adamwdraper/slide
Project-URL: Bug Tracker, https://github.com/adamwdraper/slide/issues
Author: adamwdraper
License: MIT
Classifier: Development Status :: 3 - Alpha
Classifier: Intended Audience :: Developers
Classifier: License :: OSI Approved :: MIT License
Classifier: Operating System :: OS Independent
Classifier: Programming Language :: Python :: 3
Classifier: Programming Language :: Python :: 3.11
Classifier: Programming Language :: Python :: 3.12
Classifier: Programming Language :: Python :: 3.13
Requires-Python: >=3.11
Requires-Dist: beautifulsoup4>=4.12.0
Requires-Dist: browser-use>=0.1.40
Requires-Dist: filetype>=1.2.0
Requires-Dist: httpx>=0.27.2
Requires-Dist: langchain-openai>=0.1.0
Requires-Dist: litellm>=1.75.3
Requires-Dist: pandas>=2.2.3
Requires-Dist: pdf2image>=1.17.0
Requires-Dist: platformdirs>=4.3.6
Requires-Dist: pypdf>=5.3.0
Requires-Dist: python-dotenv>=1.0.1
Requires-Dist: requests>=2.32.3
Requires-Dist: slack-sdk>=3.36.0
Requires-Dist: wandb-workspaces>=0.1.0
Requires-Dist: wandb>=0.18.0
Requires-Dist: weave>=0.52.23
Provides-Extra: dev
Requires-Dist: coverage>=7.6.10; extra == 'dev'
Requires-Dist: pytest-asyncio>=0.25.2; extra == 'dev'
Requires-Dist: pytest-cov>=6.0.0; extra == 'dev'
Requires-Dist: pytest>=8.3.4; extra == 'dev'
